tractorbeam/__init__.py
tractorbeam/_base_client.py
tractorbeam/_client.py
tractorbeam/_compat.py
tractorbeam/_constants.py
tractorbeam/_exceptions.py
tractorbeam/_files.py
tractorbeam/_models.py
tractorbeam/_qs.py
tractorbeam/_resource.py
tractorbeam/_response.py
tractorbeam/_streaming.py
tractorbeam/_types.py
tractorbeam/_version.py
tractorbeam/py.typed
tractorbeam/_utils/__init__.py
tractorbeam/_utils/_logs.py
tractorbeam/_utils/_proxy.py
tractorbeam/_utils/_reflection.py
tractorbeam/_utils/_streams.py
tractorbeam/_utils/_sync.py
tractorbeam/_utils/_transform.py
tractorbeam/_utils/_typing.py
tractorbeam/_utils/_utils.py
tractorbeam/lib/.keep
tractorbeam/resources/__init__.py
tractorbeam/resources/documents.py
tractorbeam/resources/graphs.py
tractorbeam/resources/health.py
tractorbeam/resources/queries.py
tractorbeam/types/__init__.py
tractorbeam/types/document.py
tractorbeam/types/document_contents.py
tractorbeam/types/document_create_params.py
tractorbeam/types/document_list_response.py
tractorbeam/types/document_tuples_params.py
tractorbeam/types/graph.py
tractorbeam/types/graph_add_tuples_params.py
tractorbeam/types/graph_add_tuples_response.py
tractorbeam/types/graph_create_params.py
tractorbeam/types/graph_list_response.py
tractorbeam/types/health_check_response.py
tractorbeam/types/query_create_params.py
tractorbeam/types/query_create_response.py
tractorbeam/types/query_decode_params.py
tractorbeam/types/query_decode_response.py
tractorbeam-1.1.0.dist-info/METADATA
tractorbeam-1.1.0.dist-info/WHEEL
tractorbeam-1.1.0.dist-info/licenses/LICENSE
tractorbeam-1.1.0.dist-info/RECORD
